LUMOFM/General.py
LUMOFM/Irregular_Drag.py
LUMOFM/Regular_Drag.py
LUMOFM/Sphere_Drag.py
LUMOFM/__init__.py
LUMOFM-0.1.2.dist-info/METADATA
LUMOFM-0.1.2.dist-info/WHEEL
LUMOFM-0.1.2.dist-info/top_level.txt
LUMOFM-0.1.2.dist-info/RECORD
