Metadata-Version: 2.1
Name: LUMOFM
Version: 0.1.2
Summary: Demo library
Home-page: https://LUMOFM.readthedocs.io/
Author: Akhil Marayikkottu Vijayan
Author-email: akhilmv@icloud.com
License: MIT
Classifier: Intended Audience :: Developers
Classifier: License :: OSI Approved :: MIT License
Classifier: Programming Language :: Python
Classifier: Programming Language :: Python :: 3
Classifier: Programming Language :: Python :: 3.6
Classifier: Programming Language :: Python :: 3.7
Classifier: Programming Language :: Python :: 3.8
Classifier: Programming Language :: Python :: 3.9
Classifier: Operating System :: OS Independent
Requires-Dist: numpy
